aistk/__init__.py
aistk/cli.py
aistk/core.py
aistk/events.py
aistk/io.py
aistk/schema.py
aistk/spatial.py
aistk/stats.py
aistk/stats_streaming.py
aistk/utils.py
aistk/viz.py
aistk/backends/dask_backend.py
aistk/backends/spark_backend.py
aistk/streaming/events_online.py
aistk-1.0.0.dist-info/licenses/LICENSE
aistk-1.0.0.dist-info/METADATA
aistk-1.0.0.dist-info/WHEEL
aistk-1.0.0.dist-info/entry_points.txt
aistk-1.0.0.dist-info/top_level.txt
aistk-1.0.0.dist-info/RECORD
