Metadata-Version: 2.4
Name: aistk
Version: 1.0.0
Summary: AIS Toolkit for high-resolution spatio-temporal datasets
Author: Irmina Durlik
License: 
Project-URL: Homepage, https://github.com/irmina-d/AIStk
Project-URL: Documentation, https://irmina-d.github.io/AIStk/
Project-URL: Repository, https://github.com/irmina-d/AIStk
Project-URL: Issues, https://github.com/irmina-d/AIStk/issues
Keywords: ais,maritime,tracking,polars,spatio-temporal
Classifier: Development Status :: 3 - Alpha
Classifier: Intended Audience :: Science/Research
Classifier: License :: OSI Approved :: MIT License
Classifier: Programming Language :: Python
Classifier: Programming Language :: Python :: 3
Classifier: Programming Language :: Python :: 3.9
Classifier: Programming Language :: Python :: 3.10
Classifier: Programming Language :: Python :: 3.11
Classifier: Programming Language :: Python :: 3.12
Classifier: Topic :: Scientific/Engineering :: Information Analysis
Classifier: Topic :: Scientific/Engineering :: GIS
Requires-Python: >=3.9
License-File: LICENSE
Requires-Dist: polars>=1.5.0
Requires-Dist: numpy
Requires-Dist: pyarrow
Provides-Extra: viz
Requires-Dist: folium; extra == "viz"
Provides-Extra: cli
Requires-Dist: typer; extra == "cli"
Dynamic: license-file
